{
    "has_precipitation": false,
    "temperature": 0.1,
    "downfall": 0.2,
    "effects": {
        "fog_color": 1057879,
        "sky_color": 1251111,
        "water_color": 4159204,
        "water_fog_color": 329011,
        "particle": {
            "probability": 0.01,
            "options": {
                "type": "ash"
            }
        },
        "ambient_sound": "ambient.soul_sand_valley.loop",
        "mood_sound": {
            "sound": "ambient.soul_sand_valley.mood",
            "tick_delay": 6000,
            "block_search_extent": 12,
            "offset": 4
        },
        "additions_sound": {
            "sound": "ambient.soul_sand_valley.additions",
            "tick_chance": 0.01
        },
        "music": {
            "sound": "music.nether.soul_sand_valley",
            "min_delay": 12000,
            "max_delay": 48000,
            "replace_current_music": false
        }
    },
    "carvers": [ "minecraft:nether_cave" ],
    "features": [
        [],
        [],
        [
            "minecraft:basalt_pillar"
        ],
        [
            "minecraft:fossil_upper",
            "minecraft:fossil_lower"
        ],
        [],
        [],
        [],
        [
            "goldark:abyss_lamp"
        ],
        [],
        [
            "minecraft:glow_lichen"
        ],
        []
    ],
    "creature_spawn_probability": 0.01,
    "spawners": {
        "monster": [
            {
                "type": "vex",
                "weight": 1,
                "minCount": 1,
                "maxCount": 3
            },
            {
                "type": "stray",
                "weight": 5,
                "minCount": 1,
                "maxCount": 2
            }
        ]
    },
    "spawn_costs": {
        "vex": {
            "energy_budget": 4.0,
            "charge": 0.5
        },
        "stray": {
            "energy_budget": 2.0,
            "charge": 1.0
        }
    }
}