{
    "parent": "goldark:root",
    "display": {
        "icon": {
            "id": "iron_ingot"
        },
        "title": "Proved by the Gods",
        "description": "Attain Holy Sickness' ultimate form... and survive.",
        "frame": "goal",
        "hidden": true
    },
    "criteria": {
        "requirement": {
            "trigger": "effects_changed",
            "conditions": {
                "effects": {
                    "regeneration": {},
                    "resistance": {}
                },
                "player": {
                    "nbt": "{ Tags: [ goldark.perks.holy_immune ] }"
                }
            }
        }
    },
    "rewards": {
        "experience": 20,
        "recipes": [
            "goldark:spells/judgement"
        ]
    }
}